COPYING
INSTALL.rst
MANIFEST.in
README.rst
pyproject.toml
setup.cfg
setup.py
versioneer.py
bin/zCluster
bin/zClusterBCG
bin/zClusterComparisonPlot
bin/zField
examples/400SDAll.csv
examples/400SDSmall.csv
examples/README_EXAMPLE.rst
zCluster/PhotoRedshiftEngine.py
zCluster/__init__.py
zCluster/_version.py
zCluster/catalogs.py
zCluster/clusters.py
zCluster/retrievers.py
zCluster/stellarmass.py
zCluster.egg-info/PKG-INFO
zCluster.egg-info/SOURCES.txt
zCluster.egg-info/dependency_links.txt
zCluster.egg-info/requires.txt
zCluster.egg-info/top_level.txt
zCluster/SED/BR07/default_sed1.dat
zCluster/SED/BR07/default_sed2.dat
zCluster/SED/BR07/default_sed3.dat
zCluster/SED/BR07/default_sed4.dat
zCluster/SED/BR07/default_sed5.dat
zCluster/SED/BR07/goods_sed1.dat
zCluster/SED/BR07/goods_sed2.dat
zCluster/SED/BR07/goods_sed3.dat
zCluster/SED/BR07/goods_sed4.dat
zCluster/SED/BR07/goods_sed5.dat
zCluster/SED/BR07/lrg1_sed1.dat
zCluster/SED/CWW/CWW_E_ext.sed
zCluster/SED/CWW/CWW_Im_ext.sed
zCluster/SED/CWW/CWW_Sbc_ext.sed
zCluster/SED/CWW/CWW_Scd_ext.sed
zCluster/SED/CWW/SB2_kin.sed
zCluster/SED/CWW/SB3_kin.sed
zCluster/SED/EAZY_v1.0/eazy_v1.0_sed1.dat
zCluster/SED/EAZY_v1.0/eazy_v1.0_sed2.dat
zCluster/SED/EAZY_v1.0/eazy_v1.0_sed3.dat
zCluster/SED/EAZY_v1.0/eazy_v1.0_sed4.dat
zCluster/SED/EAZY_v1.0/eazy_v1.0_sed5.dat
zCluster/SED/EAZY_v1.0/eazy_v1.0_sed6.dat
zCluster/data/redmapper_dr8_public_v5.10_catalog.fits
zCluster/data/tau0p1Gyr_m62.20
zCluster/passbands/K_2MASS.res
zCluster/passbands/RSR-W1.EE.txt
zCluster/passbands/RSR-W2.EE.txt
zCluster/passbands/RSR-W3.EE.txt
zCluster/passbands/RSR-W4.EE.txt
zCluster/passbands/VISTA_Filters_at80K_forETC_H.dat
zCluster/passbands/VISTA_Filters_at80K_forETC_J.dat
zCluster/passbands/VISTA_Filters_at80K_forETC_Ks.dat
zCluster/passbands/VISTA_Filters_at80K_forETC_Y.dat
zCluster/passbands/VISTA_Filters_at80K_forETC_Z.dat
zCluster/passbands/decam.g.am1p4.dat.txt
zCluster/passbands/decam.i.am1p4.dat.txt
zCluster/passbands/decam.r.am1p4.dat.txt
zCluster/passbands/decam.z.am1p4.dat.txt
zCluster/passbands/gDES.res
zCluster/passbands/gPS1.res
zCluster/passbands/g_CFHTLS.res
zCluster/passbands/g_SDSS.res
