Metadata-Version: 2.1
Name: zCluster
Version: 0.5.0
Summary: A code for measuring galaxy cluster photometric redshifts
Home-page: https://github.com/ACTCollaboration/zCluster
Author: Matt Hilton + zCluster contributors
Author-email: matt.hilton@wits.ac.za
License: GPL v3
Keywords: astrophysics
Classifier: Programming Language :: Python :: 3
Classifier: Environment :: Console
Classifier: Intended Audience :: Science/Research
Classifier: License :: OSI Approved :: GNU General Public License v3 (GPLv3)
Classifier: Natural Language :: English
Classifier: Operating System :: POSIX
Classifier: Topic :: Scientific/Engineering :: Astronomy
License-File: COPYING
Requires-Dist: astropy>=4.0
Requires-Dist: numpy>=1.19
Requires-Dist: matplotlib>=2.0
Requires-Dist: astLib>=0.11.10
Requires-Dist: scipy>=1.0
Requires-Dist: requests
